pithermalcam/__init__.py
pithermalcam/pi_therm_cam.py
pithermalcam/web_server.py
pithermalcam/templates/index.html
pithermalcam-1.0.0.dist-info/LICENSE
pithermalcam-1.0.0.dist-info/METADATA
pithermalcam-1.0.0.dist-info/WHEEL
pithermalcam-1.0.0.dist-info/top_level.txt
pithermalcam-1.0.0.dist-info/RECORD
