Metadata-Version: 2.1
Name: pithermalcam
Version: 1.0.0
Summary: A package which connects an MLX90640 Thermal IR Camera to a Raspberry Pi for viewing or web streaming.
Home-page: https://tomshaffner.github.io/PiThermalCam/
Author: Tom Shaffner
License: UNKNOWN
Keywords: raspberry pi mlx90640 thermal camera ir flir
Platform: UNKNOWN
Classifier: Programming Language :: Python
Classifier: Programming Language :: Python :: 3
Classifier: License :: OSI Approved :: GNU Affero General Public License v3 or later (AGPLv3+)
Classifier: Operating System :: POSIX :: Linux
Requires-Python: >=3.6
Requires-Dist: numpy (>=1.16.5)
Requires-Dist: matplotlib
Requires-Dist: scipy (>=1.6.0)
Requires-Dist: RPI.GPIO
Requires-Dist: Adafruit-Blinka
Requires-Dist: adafruit-circuitpython-mlx90640
Requires-Dist: flask
Requires-Dist: opencv-python
Requires-Dist: cmapy
